login_gmail_selenium/__init__.py
login_gmail_selenium/common/__init__.py
login_gmail_selenium/common/constant.py
login_gmail_selenium/common/log.py
login_gmail_selenium/extension/always_active.zip
login_gmail_selenium/extension/fingerprint_defender.zip
login_gmail_selenium/extension/spoof_timezone.zip
login_gmail_selenium/extension/veepn.zip
login_gmail_selenium/extension/webrtc_control.zip
login_gmail_selenium/util/__init__.py
login_gmail_selenium/util/base_profile.py
login_gmail_selenium/util/driver.py
login_gmail_selenium/util/helper.py
login_gmail_selenium/util/profiles/__init__.py
login_gmail_selenium/util/profiles/google_profile.py
login_gmail_selenium/util/profiles/profile.py
login_gmail_selenium-1.2.0.dist-info/LICENSE
login_gmail_selenium-1.2.0.dist-info/METADATA
login_gmail_selenium-1.2.0.dist-info/WHEEL
login_gmail_selenium-1.2.0.dist-info/top_level.txt
login_gmail_selenium-1.2.0.dist-info/RECORD
