Metadata-Version: 2.1
Name: login-gmail-selenium
Version: 1.2.0
Summary: A python package for login google by selenium
Home-page: https://github.com/ngminhhoang1412/LoginGmailSelenium
Author: Minh Hoang
Author-email: ngminhhoang1412@gmail.com
License: UNKNOWN
Platform: UNKNOWN
Classifier: Programming Language :: Python :: 3.9
Classifier: Operating System :: OS Independent
Classifier: License :: OSI Approved :: MIT License
License-File: LICENSE
Requires-Dist: python-dotenv (==1.0.0)
Requires-Dist: selenium (==4.8.2)
Requires-Dist: undetected-chromedriver (==3.1.5.post4)
